{
  "sessionId": "tooL8iGpKRCT",
  "clientIP": "::1",
  "createdAt": "2025-09-09T07:17:54.525Z",
  "lastModified": "2025-09-09T07:40:06.196Z",
  "layers": [
    {
      "id": "layer_1757402274651_hyqj7x",
      "type": "text",
      "name": "Sample Text",
      "visible": true,
      "properties": {
        "x": 0.1,
        "y": 0.2,
        "scale": 2.6,
        "rotation": 0,
        "opacity": 1,
        "text": "Sample Text",
        "color": "#000000",
        "fontSize": 48,
        "fontFamily": "Arial"
      },
      "imagePath": null,
      "originalPath": null,
      "createdAt": "2025-09-09T07:17:54.651Z"
    },
    {
      "id": "layer_1757402274658_ybl7f6",
      "type": "logo",
      "name": "render.jpg",
      "visible": true,
      "properties": {
        "x": 0.21564087707054153,
        "y": 0.30498775870005435,
        "scale": 0.2,
        "rotation": 0,
        "opacity": 1
      },
      "imagePath": "layer_1757402274658_ybl7f6.png",
      "originalPath": "original_uploads/layer_1757402274658_ybl7f6_original.jpg",
      "createdAt": "2025-09-09T07:17:54.659Z"
    }
  ],
  "modelSettings": {
    "modelPath": null,
    "position": {
      "x": 0,
      "y": 0,
      "z": 0
    },
    "rotation": {
      "x": 0,
      "y": 0,
      "z": 0
    }
  },
  "configuration": {},
  "lastAccessed": "2025-09-09T07:40:06.196Z"
}