{
  "sessionId": "smrSn96mRLrT",
  "clientIP": "::1",
  "createdAt": "2025-09-09T01:54:20.319Z",
  "lastModified": "2025-09-10T05:04:14.547Z",
  "layers": [
    {
      "id": "layer_1757382860438_0wtyxp",
      "type": "text",
      "name": "Sample Text",
      "visible": true,
      "properties": {
        "x": 0,
        "y": 0,
        "scale": 2.8,
        "rotation": 0,
        "opacity": 1,
        "text": "Sample Text",
        "color": "#000000",
        "fontSize": 48,
        "fontFamily": "Arial"
      },
      "imagePath": null,
      "originalPath": null,
      "createdAt": "2025-09-09T01:54:20.438Z"
    }
  ],
  "modelSettings": {
    "modelPath": null,
    "position": {
      "x": 0,
      "y": 0,
      "z": 0
    },
    "rotation": {
      "x": 0,
      "y": 0,
      "z": 0
    }
  },
  "configuration": {},
  "lastAccessed": "2025-09-10T05:04:14.547Z"
}